CHANGES.txt
bootstrap.py
buildout.cfg
setup.py
src/z3c/__init__.py
src/z3c.image.egg-info/PKG-INFO
src/z3c.image.egg-info/SOURCES.txt
src/z3c.image.egg-info/dependency_links.txt
src/z3c.image.egg-info/namespace_packages.txt
src/z3c.image.egg-info/not-zip-safe
src/z3c.image.egg-info/requires.txt
src/z3c.image.egg-info/top_level.txt
src/z3c/image/SETUP.cfg
src/z3c/image/__init__.py
src/z3c/image/configure.zcml
src/z3c/image/image.py
src/z3c/image/z3c.image-configure.zcml
src/z3c/image/proc/BROWSER.txt
src/z3c/image/proc/README.txt
src/z3c/image/proc/__init__.py
src/z3c/image/proc/adapter.py
src/z3c/image/proc/browser.py
src/z3c/image/proc/configure.zcml
src/z3c/image/proc/ftesting.zcml
src/z3c/image/proc/interfaces.py
src/z3c/image/proc/tests.py
src/z3c/image/testing/__init__.py
src/z3c/image/testing/data/flower.jpg
src/z3c/image/testing/data/hiring.gif
src/z3c/image/testing/data/locked.png