Metadata-Version: 1.0
Name: z3c.image
Version: 1.0.0
Summary: Image utils for zope3
Home-page: http://svn.zope.org/z3c.image
Author: Zope Contributors
Author-email: office@mopacreative.com
License: ZPL 2.1
Keywords: zope3 image
Platform: UNKNOWN
Classifier: Development Status :: 5 - Production/Stable
Classifier: License :: OSI Approved :: Zope Public License
Classifier: Framework :: Zope3
